graphster/__init__.py
graphster-0.0.0a0.dist-info/METADATA
graphster-0.0.0a0.dist-info/WHEEL
graphster-0.0.0a0.dist-info/top_level.txt
graphster-0.0.0a0.dist-info/RECORD
