Metadata-Version: 2.1
Name: graphster
Version: 0.0.0a0
Summary: High-performance DataGraph Library 
